keecas/__init__.py
keecas/__main__.py
keecas/cli.py
keecas/col_wrappers.py
keecas/config/__init__.py
keecas/config/manager.py
keecas/config/migration.py
keecas/config/schema.py
keecas/dataframe.py
keecas/display.py
keecas/formatters.py
keecas/label.py
keecas/localization/__init__.py
keecas/localization/languages/__init__.py
keecas/localization/languages/da.py
keecas/localization/languages/de.py
keecas/localization/languages/en.py
keecas/localization/languages/es.py
keecas/localization/languages/fr.py
keecas/localization/languages/it.py
keecas/localization/languages/nl.py
keecas/localization/languages/no.py
keecas/localization/languages/pt.py
keecas/localization/languages/sv.py
keecas/localization/pint_locale.py
keecas/pint_sympy.py
keecas/pipe_command.py
keecas/templates/minimal.ipynb
keecas/templates/quickstart.ipynb
keecas/utils.py
keecas/version.py
keecas-1.1.0.dist-info/WHEEL
keecas-1.1.0.dist-info/entry_points.txt
keecas-1.1.0.dist-info/METADATA
keecas-1.1.0.dist-info/RECORD
