Metadata-Version: 2.3
Name: keecas
Version: 1.1.0
Summary: Symbolic and units-aware calculations with LaTeX rendering for Jupyter notebooks, optimized for Quarto PDF documentation.
Author: kompre
Author-email: kompre <s.follador@gmail.com>
Classifier: Programming Language :: Python :: 3
Classifier: Programming Language :: Python :: 3.12
Classifier: Programming Language :: Python :: 3.13
Requires-Dist: pint>=0.24.3,<1.0.0
Requires-Dist: pipe>=2.2,<3.0
Requires-Dist: sympy>=1.13.1,<2.0.0
Requires-Dist: regex>=2024.7.24,<2025.0.0
Requires-Dist: ipython>=8.26.0,<9.0.0
Requires-Dist: jupyter>=1.1.1,<2.0.0
Requires-Dist: notebook>=7.2.2,<8.0.0
Requires-Dist: flatten-dict>=0.4.2,<1.0.0
Requires-Dist: ruamel-yaml>=0.18.6,<1.0.0
Requires-Dist: toml>=0.10.2
Requires-Dist: packaging>=25.0
Requires-Dist: tomlkit>=0.13.3
Requires-Python: >=3.12, <4.0
Project-URL: Documentation, https://kompre.github.io/keecas
Project-URL: Homepage, https://github.com/kompre/keecas
Project-URL: Issues, https://github.com/kompre/keecas/issues
Project-URL: Repository, https://github.com/kompre/keecas
